{"cameraMode":{"drawMode":0,"name":"Shaded","section":"Shading Mode"},"sceneLighting":true,"audioPlay":false,"sceneViewState":{"m_AlwaysRefresh":false,"showFog":true,"showSkybox":true,"showFlares":true,"showImageEffects":true,"showParticleSystems":true,"showVisualEffectGraphs":true,"m_FxEnabled":true},"in2DMode":false,"pivot":{"x":-0.034532446414232257,"y":0.06434230506420136,"z":-0.036117419600486758},"rotation":{"x":0.3125268220901489,"y":-0.34372448921203616,"z":0.12249907106161118,"w":0.877074658870697},"size":0.24352924525737763,"orthographic":false}